keydev_reports/__init__.py
keydev_reports/admin.py
keydev_reports/apps.py
keydev_reports/exporter.py
keydev_reports/file_storage.py
keydev_reports/forms.py
keydev_reports/mixins.py
keydev_reports/models.py
keydev_reports/serializers.py
keydev_reports/sql_utils.py
keydev_reports/storage.py
keydev_reports/tasks.py
keydev_reports/views.py
keydev_reports/migrations/0001_initial.py
keydev_reports/migrations/0002_reporttemplate_product.py
keydev_reports/migrations/__init__.py
keydev_reports/providers/__init__.py
keydev_reports/providers/base_provider.py
keydev_reports/providers/generate_provider.py
keydev_reports/providers/providers_config.py
keydev_reports/providers/template_provider.py
keydev_reports/report_tools/__init__.py
keydev_reports/report_tools/base_editor.py
keydev_reports/report_tools/converter.py
keydev_reports/report_tools/excel_creator.py
keydev_reports/report_tools/excel_editor.py
keydev_reports/report_tools/word_editor.py
keydev_reports/templates/keydev_reports/report_modal_form.html
keydev_reports/templates/keydev_reports/standard_report_form.html
keydev_reports-1.0.1.dist-info/METADATA
keydev_reports-1.0.1.dist-info/WHEEL
keydev_reports-1.0.1.dist-info/top_level.txt
keydev_reports-1.0.1.dist-info/RECORD
